kuaijs/__init__.py
kuaijs/action.py
kuaijs/appleocr.py
kuaijs/config.py
kuaijs/cryptoUtils.py
kuaijs/device.py
kuaijs/file.py
kuaijs/g.py
kuaijs/hid.py
kuaijs/hotupdate.py
kuaijs/image.py
kuaijs/ime.py
kuaijs/logger.py
kuaijs/media.py
kuaijs/mysql.py
kuaijs/netcard.py
kuaijs/node.py
kuaijs/paddleocr.py
kuaijs/pip.py
kuaijs/system.py
kuaijs/tomatoocr.py
kuaijs/tts.py
kuaijs/ui.py
kuaijs/utils.py
kuaijs/yolo.py
kuaijs_ios-0.3.12.dist-info/METADATA
kuaijs_ios-0.3.12.dist-info/WHEEL
kuaijs_ios-0.3.12.dist-info/top_level.txt
kuaijs_ios-0.3.12.dist-info/RECORD
